README.rst
setup.py
django_geolocation_alert.egg-info/PKG-INFO
django_geolocation_alert.egg-info/SOURCES.txt
django_geolocation_alert.egg-info/dependency_links.txt
django_geolocation_alert.egg-info/not-zip-safe
django_geolocation_alert.egg-info/pbr.json
django_geolocation_alert.egg-info/top_level.txt
geolocation/__init__.py
geolocation/middleware.py
geolocation/settings.py
geolocation/signal.py
geolocation/utils.py