Metadata-Version: 1.1
Name: django-geolocation-alert
Version: 0.5.1
Summary: Geolocation django middleware that check if user IP or agent browser change during session time.
Home-page: https://github.com/lkolacz/django-geolocation-alert.git
Author: Leszek Andrzej Kołacz
Author-email: lkolacz@gmail.com
License: MIT
Keywords: django geolocation middleware alert session hash IP agent browser
Platform: UNKNOWN
Classifier: Development Status :: 3 - Alpha
Classifier: Environment :: Web Environment
Classifier: Framework :: Django
Classifier: Framework :: Django :: 1.8
Classifier: Intended Audience :: Developers
Classifier: License :: OSI Approved :: MIT License
Classifier: Natural Language :: English
Classifier: Programming Language :: Python
Classifier: Programming Language :: Python :: 2.7
Classifier: Topic :: Security
Classifier: Topic :: System :: Monitoring
